DisambiguationCorpus
MorphologicalAnalysis
