Metadata-Version: 2.1
Name: NlpToolkit-MorphologicalAnalysis
Version: 1.0.50
Summary: Turkish Morphological Analysis
Home-page: https://github.com/StarlangSoftware/TurkishMorphologicalAnalysis-Py
Author: olcaytaner
Author-email: olcay.yildiz@ozyegin.edu.tr
License: UNKNOWN
Platform: UNKNOWN
